examples/__init__.py
ggfm/__init__.py
ggfm/conv/__init__.py
ggfm/conv/hgt_conv.py
ggfm/conv/sgformer_conv.py
ggfm/data/__init__.py
ggfm/data/graph.py
ggfm/data/hgsampling.py
ggfm/data/higpt_prompt.py
ggfm/data/lm_generate_embs.py
ggfm/data/metapath.py
ggfm/data/random_walk.py
ggfm/data/utils.py
ggfm/datasets/Amazon.py
ggfm/datasets/Aminer.py
ggfm/datasets/CiteSeer.py
ggfm/datasets/DBLP.py
ggfm/datasets/IMDB.py
ggfm/datasets/MAG.py
ggfm/datasets/OAG_CS.py
ggfm/datasets/PubMed.py
ggfm/datasets/YELP.py
ggfm/datasets/__init__.py
ggfm/datasets/cora.py
ggfm/datasets/lastFM.py
ggfm/models/__init__.py
ggfm/models/gpt_gnn.py
ggfm/models/graphgpt.py
ggfm/models/higpt.py
ggfm/models/llaga.py
ggfm/models/pt_hgnn.py
ggfm/models/sgformer.py
ggfm/models/utils.py
ggfm-0.1.8.dist-info/LICENSE
ggfm-0.1.8.dist-info/METADATA
ggfm-0.1.8.dist-info/WHEEL
ggfm-0.1.8.dist-info/top_level.txt
ggfm-0.1.8.dist-info/RECORD
